noob_utils/__init__.py
noob_utils/logger.py
noob_utils-0.0.2.dist-info/LICENSE
noob_utils-0.0.2.dist-info/METADATA
noob_utils-0.0.2.dist-info/WHEEL
noob_utils-0.0.2.dist-info/top_level.txt
noob_utils-0.0.2.dist-info/RECORD
