Metadata-Version: 2.1
Name: noob-utils
Version: 0.0.2
Summary: Common Python Utils
Home-page: https://github.com/leordsong/noom_utils
Author: Leo Song
Author-email: bjecdexlyb@gmail.com
License: MIT
Project-URL: Bug Tracker, https://github.com/leordsong/noom_utils/issues
Platform: UNKNOWN
Classifier: Programming Language :: Python :: 3
Classifier: License :: OSI Approved :: MIT License
Classifier: Operating System :: OS Independent
Requires-Python: >=3.7
License-File: LICENSE
Requires-Dist: colorama
